wordpress_rss_archiver/utils/requests_patch.py
wordpress_rss_archiver/utils/spn2.py
wordpress_rss_archiver/wordpress_rss_archiver.py
wordpress_rss_archiver-0.1.1.dist-info/METADATA
wordpress_rss_archiver-0.1.1.dist-info/WHEEL
wordpress_rss_archiver-0.1.1.dist-info/entry_points.txt
wordpress_rss_archiver-0.1.1.dist-info/RECORD
