Metadata-Version: 2.1
Name: wordpress-rss-archiver
Version: 0.1.1
Summary: 
Author: yzqzss
Author-email: yzqzss@yandex.com
Requires-Python: >=3.8,<4.0
Classifier: Programming Language :: Python :: 3
Classifier: Programming Language :: Python :: 3.8
Classifier: Programming Language :: Python :: 3.9
Classifier: Programming Language :: Python :: 3.10
Classifier: Programming Language :: Python :: 3.11
Requires-Dist: feedparser (>=6.0.10,<7.0.0)
Requires-Dist: requests (>=2.30.0,<3.0.0)
